Metadata-Version: 2.4
Name: scxpand-cuda
Version: 0.4.6
Summary: Pan-cancer detection of T-cell clonal expansion from single-cell RNA sequencing (CUDA-enabled)
Project-URL: Documentation, https://scxpand.readthedocs.io/en/latest/
Project-URL: Homepage, https://github.com/yizhak-lab-ccg/scXpand
Project-URL: Issues, https://github.com/yizhak-lab-ccg/scXpand/issues
Project-URL: Logo, https://raw.githubusercontent.com/yizhak-lab-ccg/scXpand/main/docs/images/scXpand_logo_gray.png
Project-URL: Repository, https://github.com/yizhak-lab-ccg/scXpand
Author-email: Ron Amit <ronamit@ef.technion.ac.il>, Ofir Shorer <ofirshorer@campus.technion.ac.il>
License-Expression: MIT
License-File: LICENSE
Keywords: RNA-seq,T-cell,bioinformatics,clonal-expansion,machine-learning,single-cell
Classifier: Development Status :: 4 - Beta
Classifier: Intended Audience :: Science/Research
Classifier: Operating System :: OS Independent
Classifier: Programming Language :: Python :: 3 :: Only
Classifier: Programming Language :: Python :: 3.11
Classifier: Programming Language :: Python :: 3.12
Classifier: Programming Language :: Python :: 3.13
Classifier: Topic :: Scientific/Engineering :: Artificial Intelligence
Classifier: Topic :: Scientific/Engineering :: Bio-Informatics
Requires-Python: >=3.11
Requires-Dist: anndata>=0.11.4
Requires-Dist: bbknn>=1.6
Requires-Dist: fire>=0.7
Requires-Dist: igraph>=0.11.4
Requires-Dist: lightgbm>=4.6
Requires-Dist: matplotlib>=3.10
Requires-Dist: optuna>=4.3
Requires-Dist: plotly>=6.0.1
Requires-Dist: pooch>=1.8
Requires-Dist: pydantic>=2.10.6
Requires-Dist: scanpy>=1.11.1
Requires-Dist: scikit-learn>=1.7.1
Requires-Dist: scirpy>=0.9.3
Requires-Dist: scrublet>=0.2.3
Requires-Dist: seaborn>=0.13.2
Requires-Dist: shap>=0.48
Requires-Dist: structlog>=24
Requires-Dist: tabulate>=0.9
Requires-Dist: tensorboard>=2.19
Requires-Dist: torch>=2.8.0
Requires-Dist: tqdm>=4.66
Provides-Extra: dev
Requires-Dist: cruft>=2.16; extra == 'dev'
Requires-Dist: ipykernel>=6.29.5; extra == 'dev'
Requires-Dist: ipywidgets>=8.1.5; extra == 'dev'
Requires-Dist: jupyter-client>=8.6.3; extra == 'dev'
Requires-Dist: jupyter-core>=5.7.2; extra == 'dev'
Requires-Dist: jupyter>=1.1.1; extra == 'dev'
Requires-Dist: pre-commit>=4.2; extra == 'dev'
Requires-Dist: pytest-cov>=6; extra == 'dev'
Requires-Dist: pytest-xdist>=3.6; extra == 'dev'
Requires-Dist: pytest>=8.3.4; extra == 'dev'
Requires-Dist: ruff>=0.12.7; extra == 'dev'
Provides-Extra: docs
Requires-Dist: colorama>=0.4.6; extra == 'docs'
Requires-Dist: docutils>=0.21.2; extra == 'docs'
Requires-Dist: ipython>=9.5; extra == 'docs'
Requires-Dist: myst-nb>=1.3; extra == 'docs'
Requires-Dist: myst-parser>=4.0.1; extra == 'docs'
Requires-Dist: sphinx-autobuild>=2025.8.25; extra == 'docs'
Requires-Dist: sphinx-autodoc-typehints>=3.0.1; extra == 'docs'
Requires-Dist: sphinx-book-theme>=1.1.4; extra == 'docs'
Requires-Dist: sphinx-copybutton>=0.5.2; extra == 'docs'
Requires-Dist: sphinx>=8.1.3; extra == 'docs'
Requires-Dist: sphinxcontrib-bibtex>=2.6.5; extra == 'docs'
Requires-Dist: sphinxext-opengraph>=0.13; extra == 'docs'
Requires-Dist: watchdog>=6; extra == 'docs'
